meilisearch_python_async/__init__.py
meilisearch_python_async/_http_requests.py
meilisearch_python_async/_utils.py
meilisearch_python_async/_version.py
meilisearch_python_async/client.py
meilisearch_python_async/errors.py
meilisearch_python_async/index.py
meilisearch_python_async/models/__init__.py
meilisearch_python_async/models/client.py
meilisearch_python_async/models/documents.py
meilisearch_python_async/models/health.py
meilisearch_python_async/models/index.py
meilisearch_python_async/models/search.py
meilisearch_python_async/models/settings.py
meilisearch_python_async/models/task.py
meilisearch_python_async/models/version.py
meilisearch_python_async/py.typed
meilisearch_python_async/task.py
meilisearch_python_async-1.8.0.dist-info/LICENSE
meilisearch_python_async-1.8.0.dist-info/METADATA
meilisearch_python_async-1.8.0.dist-info/WHEEL
meilisearch_python_async-1.8.0.dist-info/RECORD
