Metadata-Version: 2.1
Name: meilisearch-python-async
Version: 1.8.0
Summary: A Python async client for the Meilisearch API
Home-page: https://github.com/sanders41/meilisearch-python-async
License: MIT
Keywords: meilisearch,async,python
Author: Paul Sanders
Author-email: psanders1@gmail.com
Requires-Python: >=3.8,<4.0
Classifier: Development Status :: 5 - Production/Stable
Classifier: Intended Audience :: Developers
Classifier: License :: OSI Approved :: MIT License
Classifier: Operating System :: OS Independent
Classifier: Programming Language :: Python :: 3
Classifier: Programming Language :: Python :: 3.8
Classifier: Programming Language :: Python :: 3.9
Classifier: Programming Language :: Python :: 3.10
Classifier: Programming Language :: Python :: 3.11
Classifier: Typing :: Typed
Requires-Dist: PyJWT (>=2.3.0)
Requires-Dist: aiofiles (>=0.7)
Requires-Dist: camel-converter (>=1.0.0)
Requires-Dist: httpx (>=0.17)
Requires-Dist: pydantic (>=1.8)
Project-URL: Documentation, https://meilisearch-python-async.paulsanders.dev
Project-URL: Repository, https://github.com/sanders41/meilisearch-python-async
